Metadata-Version: 1.1
Name: jackster
Version: 0.5.0
Summary: A micro web framework.
Home-page: https://github.com/daanvdk/jackster
Author: Daan van der Kallen
Author-email: mail@daanvdk.com
License: MIT
Download-URL: https://github.com/Daanvdk/jackster/archive/0.5.tar.gz
Keywords: web,framework
Platform: UNKNOWN
